[
  {
    "question": "刘备在荆州过了几年，因为什么事情心中闷闷不乐？",
    "options": [
      "刘表不再善待他",
      "自己年华老去却没能实现抱负",
      "关羽和张飞经常争吵",
      "曹操大军逼近荆州"
    ],
    "answer": 1,
    "explanation": "原文中提到刘备在荆州过着清闲生活，看着日子流逝，自己大腿肉长肥，感慨快老了却没能干成大事业，因此心中闷闷不乐。"
  },
  {
    "question": "司马徽告诉刘备，能够帮助他平定天下的“卧龙凤雏”分别指谁？",
    "options": [
      "卧龙是庞统，凤雏是诸葛亮",
      "卧龙是诸葛亮，凤雏是庞统",
      "卧龙是徐庶，凤雏是司马徽",
      "卧龙是关羽，凤雏是张飞"
    ],
    "answer": 1,
    "explanation": "司马徽对刘备说：“这一带有卧龙，还有凤雏（音ｃｈú），您能请到其中一位，就可以平定天下了。”并告知卧龙是诸葛亮，凤雏是庞统。"
  },
  {
    "question": "徐庶告诉刘备，想要请诸葛亮出山需要怎么做？",
    "options": [
      "派人送信邀请即可",
      "亲自前往隆中拜访",
      "让张飞带着厚礼去请",
      "联合孙权一起请他"
    ],
    "answer": 1,
    "explanation": "徐庶表示诸葛亮这样的人才，必须由刘备亲自去请才能体现诚意，不能随便派人请来。"
  },
  {
    "question": "诸葛亮的老家琅琊郡阳都县，也就是现在的哪里？",
    "options": [
      "山东沂水县南",
      "湖北襄阳西",
      "河南新野县",
      "江西九江西南"
    ],
    "answer": 0,
    "explanation": "原文提到诸葛亮的老家在琅琊郡阳都县（今山东沂水县南）。"
  },
  {
    "question": "刘备一共几次前往隆中拜访诸葛亮，最终才见到他？",
    "options": [
      "一次",
      "两次",
      "三次",
      "四次"
    ],
    "answer": 2,
    "explanation": "刘备第一次拜访扑空，第二次再去也没见到，第三次才成功见到诸葛亮。"
  },
  {
    "question": "隆中对策中，诸葛亮认为目前不能和曹操直接争锋的原因不包括以下哪一项？",
    "options": [
      "曹操拥有百万兵力",
      "曹操挟天子以令诸侯",
      "曹操占据江东地势险要之地",
      "曹操已经战胜袁绍实力强大"
    ],
    "answer": 2,
    "explanation": "诸葛亮指出曹操拥有百万兵力且挟天子发号施令，不能光凭武力争锋，而江东是孙权占据的地盘，荆州益州才是可以图谋的地方。"
  },
  {
    "question": "诸葛亮在隆中对策中提出刘备可以夺取哪两个州作为基业？",
    "options": [
      "荆州和益州",
      "徐州和兖州",
      "江东和荆州",
      "益州和江东"
    ],
    "answer": 0,
    "explanation": "诸葛亮分析了荆州和益州的形势，认为这两个州是可以夺取作为基业的地方。"
  },
  {
    "question": "刘备在拜访诸葛亮成功后，将自己和诸葛亮的关系比作什么？",
    "options": [
      "鱼和水",
      "伯乐和千里马",
      "兄弟和手足",
      "君主和臣子"
    ],
    "answer": 0,
    "explanation": "刘备对关羽张飞说：“我有了孔明先生，就像鱼得到水一样。”"
  },
  {
    "question": "官渡大战后刘备投奔刘表，刘表为刘备提供了人马让他驻守在哪里？",
    "options": [
      "新野",
      "江陵",
      "樊城",
      "夏口"
    ],
    "answer": 0,
    "explanation": "原文提到“刘表拨给他一些人马，让他驻在新野（今河南新野县）。”"
  },
  {
    "question": "以下哪位人物没有向刘备推荐过诸葛亮？",
    "options": [
      "司马徽",
      "徐庶",
      "庞统",
      "诸葛亮自己"
    ],
    "answer": 2,
    "explanation": "司马徽和徐庶都向刘备推荐了诸葛亮，庞统并没有向刘备推荐过诸葛亮。"
  }
]